functional_itertools/__init__.py
functional_itertools/classes.py
functional_itertools/errors.py
functional_itertools/utilities.py
tests/classes/__init__.py
tests/classes/test_cattrs.py
tests/classes/test_cdict.py
tests/classes/test_cfrozenset.py
tests/classes/test_citerable.py
tests/classes/test_clist.py
tests/classes/test_cset.py
tests/methods/__init__.py
tests/methods/test_builtins.py
tests/methods/test_extra_public.py
tests/methods/test_functools.py
tests/methods/test_itertools.py
tests/methods/test_itertools_recipes.py
tests/methods/test_more_itertools.py
tests/methods/test_multiprocessing.py
tests/methods/test_pathlib.py
functional_itertools-0.11.1.dist-info/METADATA
functional_itertools-0.11.1.dist-info/WHEEL
functional_itertools-0.11.1.dist-info/top_level.txt
functional_itertools-0.11.1.dist-info/RECORD
