Metadata-Version: 2.1
Name: functional-itertools
Version: 0.11.1
Summary: Python collections in a functional-programming style
Home-page: UNKNOWN
Author: Bao Wei
Author-email: baowei.ur521@gmail.com
License: MIT
Platform: UNKNOWN
Requires-Python: >=3.8
Requires-Dist: attrs (>=19.3)
Requires-Dist: more-itertools (>=8.2)
